{
  "version": "1.0.0",
  "build_date": "2025-09-10",
  "build_time": "13:26:00",
  "executable_name": "SincronizadorBiometricoV1.exe",
  "executable_size_mb": 20.7,
  "source_file": "sincronizador_biometrico_mejorado.py",
  "spec_file": "SincronizadorBiometricoV1.spec",
  "python_version": "3.11.9",
  "pyinstaller_version": "6.14.2",
  "platform": "Windows-10",
  "architecture": "64-bit",
  "compilation_mode": "onefile",
  "console_window": false,
  "icon_included": true,
  "upx_compression": true,
  "dependencies_included": [
    "tkinter",
    "tkinter.ttk",
    "tkinter.messagebox", 
    "tkinter.filedialog",
    "threading",
    "json",
    "requests",
    "logging",
    "logging.handlers",
    "time",
    "datetime",
    "socket",
    "subprocess",
    "pystray",
    "PIL",
    "PIL.Image",
    "PIL.ImageDraw",
    "sys",
    "os",
    "zk",
    "winreg",
    "tempfile"
  ],
  "excluded_libraries": [
    "matplotlib",
    "numpy", 
    "scipy",
    "pandas"
  ],
  "features_included": [
    "Persistencia mejorada de configuración",
    "Auto-guardado periódico",
    "Inicio automático con Windows",
    "Minimización a bandeja del sistema",
    "Logging detallado",
    "Sincronización automática",
    "Conexión robusta con dispositivo biométrico",
    "Interfaz gráfica completa",
    "Gestión de errores mejorada",
    "Sistema de pruebas integrado"
  ],
  "startup_configuration": {
    "method": "Windows Task Scheduler",
    "trigger": "LogonTrigger",
    "delay": "30 seconds",
    "fallback": "Registry entry",
    "task_name": "SincronizadorBiometricoV1"
  },
  "paths": {
    "executable": "C:\\Users\\Entrecables y Redes\\Documents\\GitHub\\Sync_Bio\\dist\\SincronizadorBiometricoV1.exe",
    "config": "C:\\Users\\Entrecables y Redes\\Documents\\GitHub\\Sync_Bio\\dist\\biometrico_config.json",
    "logs": "C:\\Users\\Entrecables y Redes\\Documents\\GitHub\\Sync_Bio\\dist\\logs\\biometrico_sync.log"
  },
  "version_info": {
    "file_version": "1.0.0.0",
    "product_version": "1.0.0.0",
    "file_description": "Sincronizador Biométrico V1",
    "product_name": "Sincronizador Biométrico",
    "company_name": "Entrecables y Redes",
    "copyright": "© 2025 Entrecables y Redes",
    "internal_name": "SincronizadorBiometricoV1",
    "original_filename": "SincronizadorBiometricoV1.exe"
  },
  "compilation_notes": "Compilación exitosa con todas las correcciones implementadas para persistencia y autostart",
  "tested_on": "Windows 10",
  "status": "Production Ready"
}
